torchorthopolys-0.3.dist-info/METADATA
torchorthopolys-0.3.dist-info/WHEEL
torchorthopolys-0.3.dist-info/entry_points.txt
torchorthopolys-0.3.dist-info/licenses/LICENSE
torchorthopolys/__init__.py
torchorthopolys/orthopolys.py
torchorthopolys/util.py
torchorthopolys-0.3.dist-info/RECORD
